lebsta_units/__init__.py
lebsta_units-1.1.2.dist-info/licenses/LICENSE
lebsta_units-1.1.2.dist-info/METADATA
lebsta_units-1.1.2.dist-info/WHEEL
lebsta_units-1.1.2.dist-info/top_level.txt
lebsta_units-1.1.2.dist-info/RECORD
